{
  "display": {
    "icon": {
      "item": "minecraft:blaze_powder"
    },
    "title": {
      "translate": "advancements.gimme_dat_powda.title"
    },
    "description": {
      "translate": "advancements.gimme_dat_powda.descr"
    },
    "frame": "task",
    "show_toast": true,
    "announce_to_chat": true,
    "hidden": false
  },
  "criteria": {
    "gimme_dat_powda_0": {
      "trigger": "minecraft:inventory_changed",
      "conditions": {
        "items": [
          {
            "items": [
              "minecraft:blaze_powder"
            ],
            "count": {
              "min": 1,
              "max": 64
            }
          }
        ]
      }
    }
  },
  "parent": "stmwr:creation_at_your_fingertips"
}